goplus/__init__.py
goplus/gpio.py
goplus/mqtt.py
goplus/things.py
goplus_py-0.1.0.dist-info/DESCRIPTION.rst
goplus_py-0.1.0.dist-info/METADATA
goplus_py-0.1.0.dist-info/RECORD
goplus_py-0.1.0.dist-info/WHEEL
goplus_py-0.1.0.dist-info/metadata.json
goplus_py-0.1.0.dist-info/top_level.txt
