Metadata-Version: 2.0
Name: goplus-py
Version: 0.1.0
Summary: Python SDK for GOPLUSPLATFORM
Home-page: http://goplusplatform.com/
Author: Go Plus Platform
Author-email: info@goplusplatform.com
License: Apache Software License
Keywords: goplus iot platform sdk
Platform: UNKNOWN
Classifier: Development Status :: 4 - Beta
Classifier: Intended Audience :: Developers
Classifier: Natural Language :: English
Classifier: License :: OSI Approved :: Apache Software License
Classifier: Operating System :: OS Independent
Classifier: Programming Language :: Python :: 2.7
Classifier: Programming Language :: Python :: 3
Classifier: Programming Language :: Python :: 3.3
Classifier: Programming Language :: Python :: 3.4
Classifier: Programming Language :: Python :: 3.5
Classifier: Topic :: Software Development :: Libraries :: Python Modules
Requires-Dist: paho-mqtt
Requires-Dist: requests
Provides-Extra: rpi
Requires-Dist: RPi.GPIO; extra == 'rpi'
